fastapi_authenticator/__init__.py
gcp_taskqueue/__init__.py
gcp_taskqueue-0.0.3.dist-info/LICENSE
gcp_taskqueue-0.0.3.dist-info/METADATA
gcp_taskqueue-0.0.3.dist-info/WHEEL
gcp_taskqueue-0.0.3.dist-info/top_level.txt
gcp_taskqueue-0.0.3.dist-info/RECORD
