Metadata-Version: 2.1
Name: gcp-taskqueue
Version: 0.0.3
Summary: google cloud task queue
Home-page: https://github.com/guyingbo/gcp-taskqueue
Author: Yingbo Gu
Author-email: tensiongyb@gmail.com
Maintainer: Yingbo Gu
Maintainer-email: tensiongyb@gmail.com
License: MIT
Platform: UNKNOWN
Classifier: License :: OSI Approved :: MIT License
Classifier: Intended Audience :: Developers
Classifier: Programming Language :: Python :: 3.6
Classifier: Programming Language :: Python :: 3.7
Classifier: Programming Language :: Python :: 3.8
Requires-Python: >=3.6
Requires-Dist: google-cloud-tasks
Requires-Dist: google-auth
